README.md
setup.py
aasaanjobs_notificationhub.egg-info/PKG-INFO
aasaanjobs_notificationhub.egg-info/SOURCES.txt
aasaanjobs_notificationhub.egg-info/dependency_links.txt
aasaanjobs_notificationhub.egg-info/requires.txt
aasaanjobs_notificationhub.egg-info/top_level.txt
notificationhub_sdk/__init__.py
notificationhub_sdk/base.py
notificationhub_sdk/common.py
notificationhub_sdk/aws/__init__.py
notificationhub_sdk/aws/session.py
notificationhub_sdk/aws/sqs.py
notificationhub_sdk/chatbot/__init__.py
notificationhub_sdk/chatbot/chatbot.py
notificationhub_sdk/chatbot/chatbot_whatsapp.py
notificationhub_sdk/email_task/__init__.py
notificationhub_sdk/email_task/email.py
notificationhub_sdk/mobile_push/__init__.py
notificationhub_sdk/mobile_push/push.py
notificationhub_sdk/proto/__init__.py
notificationhub_sdk/proto/notification_hub_pb2.py
notificationhub_sdk/sms/__init__.py
notificationhub_sdk/sms/sms.py
notificationhub_sdk/task/__init__.py
notificationhub_sdk/task/task.py
notificationhub_sdk/whatsapp/__init__.py
notificationhub_sdk/whatsapp/whatsapp.py