Metadata-Version: 2.1
Name: aasaanjobs-notificationhub
Version: 1.3.0
Summary: Python client for Aasaanjobs/Waahjobs Notification Hub
Home-page: https://github.com/aasaanjobs/notification-hub-py-sdk
Author: Raghav Nayak, Sohel tarir
Author-email: api@olxpeople.com
License: UNKNOWN
Platform: UNKNOWN
Classifier: Development Status :: 3 - Alpha
Classifier: Intended Audience :: Developers
Classifier: Programming Language :: Python :: 3.5
Classifier: Programming Language :: Python :: 3.6
Classifier: Programming Language :: Python :: 3.7
Requires-Python: >=3.5
